{
	"animations": [
		{
			"loop": false,
			"offsets": [
				-31,
				114
			],
			"anim": "idle",
			"fps": 24,
			"name": "Idle",
			"indices": []
		},
		{
			"loop": false,
			"offsets": [
				32,
				82
			],
			"anim": "singLEFT",
			"fps": 24,
			"name": "left",
			"indices": []
		},
		{
			"loop": false,
			"offsets": [
				25,
				-52
			],
			"anim": "singDOWN",
			"fps": 24,
			"name": "down",
			"indices": []
		},
		{
			"loop": false,
			"offsets": [
				-42,
				78
			],
			"anim": "singRIGHT",
			"fps": 24,
			"name": "right",
			"indices": []
		},
		{
			"loop": false,
			"offsets": [
				-3,
				138
			],
			"anim": "singUP",
			"fps": 24,
			"name": "up",
			"indices": []
		},
		{
			"offsets": [
				-31,
				114
			],
			"indices": [
				10,
				11,
				12,
				13
			],
			"fps": 24,
			"anim": "idle-loop",
			"loop": true,
			"name": "Idle"
		},
		{
			"offsets": [
				32,
				82
			],
			"indices": [
				4,
				5,
				6,
				7
			],
			"fps": 24,
			"anim": "singLEFT-loop",
			"loop": true,
			"name": "left"
		},
		{
			"offsets": [
				25,
				-52
			],
			"indices": [
				4,
				5,
				6,
				7
			],
			"fps": 24,
			"anim": "singDOWN-loop",
			"loop": true,
			"name": "down"
		},
		{
			"offsets": [
				-42,
				78
			],
			"indices": [
				4,
				5,
				6,
				7
			],
			"fps": 24,
			"anim": "singRIGHT-loop",
			"loop": true,
			"name": "right"
		},
		{
			"offsets": [
				-3,
				138
			],
			"indices": [
				4,
				5,
				6,
				7
			],
			"fps": 24,
			"anim": "singUP-loop",
			"loop": true,
			"name": "up"
		}
	],
	"no_antialiasing": false,
	"image": "characters/skarlet_excited",
	"position": [
		50,
		150
	],
	"healthicon": "skarlet",
	"flip_x": false,
	"healthbar_colors": [
		225,
		47,
		106
	],
	"camera_position": [
		220,
		0
	],
	"sing_duration": 4,
	"scale": 1
}